setup.py
json_table_schema.egg-info/PKG-INFO
json_table_schema.egg-info/SOURCES.txt
json_table_schema.egg-info/dependency_links.txt
json_table_schema.egg-info/top_level.txt
jsontableschema/__init__.py