Metadata-Version: 1.0
Name: json-table-schema
Version: 0.1
Summary: Python library for dealing with JSON Table Schema files
Home-page: UNKNOWN
Author: Martin Keegan
Author-email: martin.keegan@okfn.org
License: Apache Licence v2.0
Platform: UNKNOWN
